{
  "stage": "Stage 3: Endpoints Identified",
  "timestamp": "20251202_084604",
  "pages_with_endpoints": [
    {
      "page_name": "Homepage",
      "description": "Displays the current date and time fetched from the Flask backend server.",
      "requirements": [
        "Display current date",
        "Display current time",
        "Fetch data from Flask backend server",
        "Visually appealing design",
        "Responsive layout",
        "Clear and readable font",
        "Accurate date and time update",
        "Error handling for backend server connection"
      ],
      "backend_endpoints": [
        {
          "endpoint_name": "Get Current Date",
          "description": "Returns the current date",
          "method": "GET",
          "path": "/api/current-date"
        },
        {
          "endpoint_name": "Get Current Time",
          "description": "Returns the current time",
          "method": "GET",
          "path": "/api/current-time"
        },
        {
          "endpoint_name": "Get Current Date and Time",
          "description": "Returns the current date and time",
          "method": "GET",
          "path": "/api/current-datetime"
        },
        {
          "endpoint_name": "Health Check",
          "description": "Checks if the backend server is running and returns a success response",
          "method": "GET",
          "path": "/api/health-check"
        }
      ]
    },
    {
      "page_name": "Error Page",
      "description": "Handles and displays any errors that occur during data fetching or application execution.",
      "requirements": [
        "Display error message",
        "Show error code",
        "Provide retry option",
        "Include link to homepage",
        "Maintain visually appealing design",
        "Display error details",
        "Option to report error"
      ],
      "backend_endpoints": [
        {
          "endpoint_name": "Get Error Details",
          "description": "Fetch error details to display on the error page",
          "method": "GET",
          "path": "/api/error/details"
        },
        {
          "endpoint_name": "Report Error",
          "description": "Send error report to the server",
          "method": "POST",
          "path": "/api/error/report"
        },
        {
          "endpoint_name": "Retry Request",
          "description": "Retry the failed request",
          "method": "POST",
          "path": "/api/error/retry"
        },
        {
          "endpoint_name": "Get Homepage Link",
          "description": "Get the link to the homepage",
          "method": "GET",
          "path": "/api/homepage/link"
        }
      ]
    },
    {
      "page_name": "About Page",
      "description": "Provides information about the application and its features.",
      "requirements": [
        "Display application name and logo",
        "Include a brief description of the application",
        "List the key features of the application",
        "Provide information about the technologies used (React and Flask)",
        "Display a visually appealing design with proper typography and color scheme",
        "Ensure responsive design for various screen sizes and devices",
        "Include a section for displaying the current date and time",
        "Add a call-to-action (CTA) button for navigation to other pages or features"
      ],
      "backend_endpoints": [
        {
          "endpoint_name": "Get Application Info",
          "description": "Retrieve application name, logo, and description",
          "method": "GET",
          "path": "/api/app-info"
        },
        {
          "endpoint_name": "Get Key Features",
          "description": "Retrieve list of key features of the application",
          "method": "GET",
          "path": "/api/key-features"
        },
        {
          "endpoint_name": "Get Technologies Used",
          "description": "Retrieve information about the technologies used in the application",
          "method": "GET",
          "path": "/api/technologies-used"
        },
        {
          "endpoint_name": "Get Current Date and Time",
          "description": "Retrieve the current date and time",
          "method": "GET",
          "path": "/api/current-datetime"
        }
      ]
    },
    {
      "page_name": "Loading Screen",
      "description": "Displays a loading animation while the application fetches data from the backend server.",
      "requirements": [
        "Display a visually appealing loading animation",
        "Show a progress indicator or a loading message",
        "Have a consistent design language throughout the application",
        "Be accessible on various devices and screen sizes",
        "Display for a limited time until data is fetched from the backend server",
        "Have a smooth transition to the main page after loading is complete"
      ],
      "backend_endpoints": [
        {
          "endpoint_name": "Fetch Initial Data",
          "description": "Fetches the initial data required for the application to load",
          "method": "GET",
          "path": "/api/init"
        },
        {
          "endpoint_name": "Check Data Availability",
          "description": "Checks if the required data is available and ready to be fetched",
          "method": "GET",
          "path": "/api/data/ready"
        },
        {
          "endpoint_name": "Get Loading Progress",
          "description": "Returns the loading progress as a percentage",
          "method": "GET",
          "path": "/api/loading/progress"
        }
      ]
    }
  ]
}